nokufind/Comment.py
nokufind/Finder.py
nokufind/Note.py
nokufind/Post.py
nokufind/__init__.py
nokufind/Subfinder/DanbooruFinder.py
nokufind/Subfinder/GelbooruFinder.py
nokufind/Subfinder/KonachanFinder.py
nokufind/Subfinder/ManganatoFinder.py
nokufind/Subfinder/NHentaiFinder.py
nokufind/Subfinder/PixivFinder.py
nokufind/Subfinder/Rule34Finder.py
nokufind/Subfinder/Subfinder.py
nokufind/Subfinder/YandereFinder.py
nokufind/Subfinder/__init__.py
nokufind/Utils/PixivAuth.py
nokufind/Utils/Rule34API.py
nokufind/Utils/Utils.py
nokufind/Utils/__init__.py
tests/__init__.py
nokufind-1.0.5.dist-info/LICENSE
nokufind-1.0.5.dist-info/METADATA
nokufind-1.0.5.dist-info/WHEEL
nokufind-1.0.5.dist-info/top_level.txt
nokufind-1.0.5.dist-info/RECORD
